Homework2/alu_top/alu.sv
// 1-bit ALU behavioral code
`timescale 1ns/1ps
module alu // Module start declaration
#(parameter N=4) // Parameter declaration
(
  input logic[N-1:0] operand1, operand2,
  input logic[1:0] operation,
  output logic[N-1:0] alu_out
);
  always@(operand1 or operand2 or operation) 
  begin
    case(operation)
      2'b00: alu_out = operand1 + operand2; 
      2'b01: alu_out = operand1 - operand2; 
      2'b10: alu_out = operand1 & operand2;
      2'b11: alu_out = operand1 | operand2; 
    endcase
  end
endmodule: alu

Homework2/alu_top/alu_top.sv
// N-bit ALU behavioral code
`timescale 1ns/1ps
module alu_top // Module start declaration
#(parameter N=4) // Parameter declaration
( input logic clk, reset,
   input logic[N-1:0]operand1, operand2,
   input logic[1:0] operation,
   output logic[N-1:0] result
);

  // Local net declaration
  logic[N-1:0] alu_out; 

  // Instantiation of module alu
  alu #(.N(N)) alu_instance(
    .*
  );

  // Register alu output	
  always@(posedge clk or posedge reset) begin
    if(reset == 1) begin
      result <= 0;
    end
    else begin
      result <= alu_out;
    end
  end
endmodule: alu_top // Module alu_top end declaration

Homework2/alu_top/alu_top_testbench.sv
//1-bit ALU testbench code
`timescale 1ns/1ps
module alu_top_testbench;
parameter N = 1;
logic clock, reset;
logic [N-1:0] operand1, operand2;
logic [N-1:0] result;
logic [1:0] operation;

// Instantiate design under test
alu_top #(.N(N)) design_instance(
 .clk(clock),
 .reset(reset),
 .operand1(operand1), 
 .operand2(operand2), 
 .operation(operation), 
 .result(result)
);

initial begin
// Initialize Inputs
reset = 1;
clock = 0;
operand1 = 0;
operand2 = 0;
operation = 0;

// Wait 20 ns for global reset to finish and start counter
#20ns;
reset = 0;

#20ns
operand1 = 0;
operand2 = 1;
operation = 0;

#20ns;
operand1 = 1;
operand2 = 1;
operation = 1;

#20ns;
operand1 = 1;
operand2 = 1;
operation = 2;

#20ns;
operand1 = 1;
operand2 = 0;
operation = 3;

// Wait for 10ns
#20ns;

// terminate simulation
$finish();
end

// Clock generator logic
always@(clock) begin
  #10ns clock <= !clock;
end

// Print input and output signals
initial begin
 $monitor(" time=%0t,  clk=%b  reset=%b  operation=%d, operand1=%d, operand2=%d, result=%d",$time, clock, reset, operation, operand1, operand2, result);
end
endmodule

Homework2/alu_top/alu_top.vcd
$date
	Sat Jan 20 19:21:44 2024
$end
$version
	Icarus Verilog
$end
$timescale
	1ps
$end
$scope module alu_top_testbench $end
$var wire 1 ! result $end
$var parameter 32 " N $end
$var reg 1 # clock $end
$var reg 1 $ operand1 $end
$var reg 1 % operand2 $end
$var reg 2 & operation [1:0] $end
$var reg 1 ' reset $end
$scope module design_instance $end
$var wire 1 # clk $end
$var wire 1 $ operand1 $end
$var wire 1 % operand2 $end
$var wire 2 ( operation [1:0] $end
$var wire 1 ' reset $end
$var wire 1 ) alu_out $end
$var parameter 32 * N $end
$var reg 1 ! result $end
$scope module alu_instance $end
$var wire 1 $ operand1 $end
$var wire 1 % operand2 $end
$var wire 2 + operation [1:0] $end
$var parameter 32 , N $end
$var reg 1 ) alu_out $end
$upscope $end
$upscope $end
$upscope $end
$enddefinitions $end
$comment Show the parameter values. $end
$dumpall
b1 ,
b1 *
b1 "
$end
#0
$dumpvars
b0 +
0)
b0 (
1'
b0 &
0%
0$
0#
0!
$end
#10000
1#
#20000
0#
0'
#30000
1#
#40000
0#
1)
1%
#50000
1!
1#
#60000
0#
0)
b1 &
b1 (
b1 +
1$
#70000
0!
1#
#80000
0#
1)
b10 &
b10 (
b10 +
#90000
1!
1#
#100000
0#
b11 &
b11 (
b11 +
0%
