Homework5/lfsr.sv
//Linear Feedback Shift Register
module lfsr
#(parameter N = 4) // Number of bits for LFSR should support N = 2...8
(
  input logic clk, reset_n, load_seed,
  input logic[N-1:0] seed_data,
  output logic lfsr_done,
  output logic[N-1:0] lfsr_data
);

logic[N-1:0] my_lfsr_data;
logic[N-1:0] next_lfsr_data;

always @(negedge reset_n) 
begin
  my_lfsr_data = {N{1'b1}};
end

always @(posedge clk)
begin
  if (load_seed)
    my_lfsr_data = seed_data;
  else begin
    case (N)
      2: my_lfsr_data = {my_lfsr_data[N-1:0], my_lfsr_data[N-1] ^ my_lfsr_data[0]};
      3: my_lfsr_data = {my_lfsr_data[N-1:0], my_lfsr_data[N-1] ^ my_lfsr_data[1]};
      4: my_lfsr_data = {my_lfsr_data[N-1:0], my_lfsr_data[N-1] ^ my_lfsr_data[2]};
      5: my_lfsr_data = {my_lfsr_data[N-1:0], my_lfsr_data[N-1] ^ my_lfsr_data[2]};
      6: my_lfsr_data = {my_lfsr_data[N-1:0], my_lfsr_data[N-1] ^ my_lfsr_data[4]};
      7: my_lfsr_data = {my_lfsr_data[N-1:0], my_lfsr_data[N-1] ^ my_lfsr_data[5]};
      8: my_lfsr_data = {my_lfsr_data[N-1:0], my_lfsr_data[N-1] ^ my_lfsr_data[5] ^  my_lfsr_data[4] ^  my_lfsr_data[3]};
    endcase

    case (N)
      2: next_lfsr_data = {my_lfsr_data[N-1:0], my_lfsr_data[N-1] ^ my_lfsr_data[0]};
      3: next_lfsr_data = {my_lfsr_data[N-1:0], my_lfsr_data[N-1] ^ my_lfsr_data[1]};
      4: next_lfsr_data = {my_lfsr_data[N-1:0], my_lfsr_data[N-1] ^ my_lfsr_data[2]};
      5: next_lfsr_data = {my_lfsr_data[N-1:0], my_lfsr_data[N-1] ^ my_lfsr_data[2]};
      6: next_lfsr_data = {my_lfsr_data[N-1:0], my_lfsr_data[N-1] ^ my_lfsr_data[4]};
      7: next_lfsr_data = {my_lfsr_data[N-1:0], my_lfsr_data[N-1] ^ my_lfsr_data[5]};
      8: next_lfsr_data = {my_lfsr_data[N-1:0], my_lfsr_data[N-1] ^ my_lfsr_data[5] ^  my_lfsr_data[4] ^  my_lfsr_data[3]};
    endcase

    if (next_lfsr_data == seed_data)
      lfsr_done = 1;
    else  
      lfsr_done = 0;
  end
end

assign lfsr_data = my_lfsr_data;

//Guidance on translating polynomials to HW though pseudocodes below
//For N=4: polynomial is x^4+ x^3 + 1
//the corrresponding pseudo-code for XOR gate given below. Notice that the index used is one less than the equation
	//xor_output = lfsr_data[3] ^ lfsr_data[2];
	
//Another example, when N=5, the correponding polynomial is x^5 + x^3 + 1
//this polynomial will yield XOR hardware shown by pseudo code below
	//xor_output = lfsr_data[4] ^ lfsr_data[2];
	
//Note: We are tapping indexes which are one less than the exponent. This is because the numbering for the polynomial exponents starts from 1 and goes till N....whereas, the numbering convention we follow is starting from 0 going up to N-1. 

//student to add implementation for LFSR code below

initial begin
	$dumpfile("dump.vcd.tmp");
	$dumpvars;
end

endmodule: lfsr

Homework5/lfsr_testbench.sv
`timescale 1ns/1ns
//LFSR Testbench Code
module lfsr_testbench;
  parameter N = 4;
  logic clock;
  logic [N-1:0] lfsr_data, seed_data;
  logic lfsr_done;
  logic reset_n, load_seed;
   
  lfsr #(.N(N)) design_inst(
   .clk(clock),
   .reset_n(reset_n),
   .load_seed(load_seed),
   .seed_data(seed_data),
   .lfsr_data(lfsr_data),
   .lfsr_done(lfsr_done)
  );
  
  initial begin
   // Initialize Inputs
   reset_n = 0;
   load_seed = 0;
   clock = 0;
   seed_data = {N{1'b0}};

   // Wait 10 ns for global reset_n to finish and start counter
   #15;
   reset_n = 1;

   #10;
   load_seed = 1;
   seed_data = {N{1'b1}}; //Change value to change seed
   // seed_data = {N{1'b0}};

   #20;
   load_seed = 0;

	for (int i=0 ; i <2**(N-2) ; i++)
	begin
		#160;
	end
   // terminate simulation
   $finish();
  end

  // Clock generator logic
  always@(clock) begin
    #10ns clock <= !clock;
  end

  // Print input and output signals
  always@(posedge clock or reset_n or load_seed) begin
   $display(" time=%0t,  reset_n=%b  clk=%b  load_seed=%b  count=%d  lfsr_done=%b, lfsr_data=%b", $time, reset_n, clock, load_seed, lfsr_data, lfsr_done, lfsr_data);
  end

endmodule

Homework5/lfsr.vcd
$date
	Sat Feb 10 20:38:31 2024
$end
$version
	Icarus Verilog
$end
$timescale
	1ns
$end
$scope module lfsr_testbench $end
$var wire 1 ! lfsr_done $end
$var wire 4 " lfsr_data [3:0] $end
$var parameter 32 # N $end
$var reg 1 $ clock $end
$var reg 1 % load_seed $end
$var reg 1 & reset_n $end
$var reg 4 ' seed_data [3:0] $end
$scope module design_inst $end
$var wire 1 $ clk $end
$var wire 4 ( lfsr_data [3:0] $end
$var wire 1 % load_seed $end
$var wire 1 & reset_n $end
$var wire 4 ) seed_data [3:0] $end
$var parameter 32 * N $end
$var reg 1 ! lfsr_done $end
$var reg 4 + my_lfsr_data [3:0] $end
$var reg 4 , next_lfsr_data [3:0] $end
$upscope $end
$scope begin $ivl_for_loop0 $end
$var integer 32 - i [31:0] $end
$upscope $end
$upscope $end
$enddefinitions $end
$comment Show the parameter values. $end
$dumpall
b100 *
b100 #
$end
#0
$dumpvars
b0 -
bx ,
b1111 +
b0 )
b1111 (
b0 '
0&
0%
0$
b1111 "
x!
$end
#10
0!
b1100 ,
b1110 "
b1110 (
b1110 +
1$
#15
1&
#20
0$
#25
b1111 '
b1111 )
1%
#30
b1111 "
b1111 (
b1111 +
1$
#40
0$
#45
0%
#50
b1110 "
b1110 (
b1110 +
1$
#60
0$
#70
b1000 ,
b1100 "
b1100 (
b1100 +
1$
#80
0$
#90
b1 ,
b1000 "
b1000 (
b1000 +
1$
#100
0$
#110
b10 ,
b1 "
b1 (
b1 +
1$
#120
0$
#130
b100 ,
b10 "
b10 (
b10 +
1$
#140
0$
#150
b1001 ,
b100 "
b100 (
b100 +
1$
#160
0$
#170
b11 ,
b1001 "
b1001 (
b1001 +
1$
#180
0$
#190
b110 ,
b11 "
b11 (
b11 +
1$
#200
0$
#205
b1 -
#210
b1101 ,
b110 "
b110 (
b110 +
1$
#220
0$
#230
b1010 ,
b1101 "
b1101 (
b1101 +
1$
#240
0$
#250
b101 ,
b1010 "
b1010 (
b1010 +
1$
#260
0$
#270
b1011 ,
b101 "
b101 (
b101 +
1$
#280
0$
#290
b111 ,
b1011 "
b1011 (
b1011 +
1$
#300
0$
#310
1!
b1111 ,
b111 "
b111 (
b111 +
1$
#320
0$
#330
0!
b1110 ,
b1111 "
b1111 (
b1111 +
1$
#340
0$
#350
b1100 ,
b1110 "
b1110 (
b1110 +
1$
#360
0$
#365
b10 -
#370
b1000 ,
b1100 "
b1100 (
b1100 +
1$
#380
0$
#390
b1 ,
b1000 "
b1000 (
b1000 +
1$
#400
0$
#410
b10 ,
b1 "
b1 (
b1 +
1$
#420
0$
#430
b100 ,
b10 "
b10 (
b10 +
1$
#440
0$
#450
b1001 ,
b100 "
b100 (
b100 +
1$
#460
0$
#470
b11 ,
b1001 "
b1001 (
b1001 +
1$
#480
0$
#490
b110 ,
b11 "
b11 (
b11 +
1$
#500
0$
#510
b1101 ,
b110 "
b110 (
b110 +
1$
#520
0$
#525
b11 -
#530
b1010 ,
b1101 "
b1101 (
b1101 +
1$
#540
0$
#550
b101 ,
b1010 "
b1010 (
b1010 +
1$
#560
0$
#570
b1011 ,
b101 "
b101 (
b101 +
1$
#580
0$
#590
b111 ,
b1011 "
b1011 (
b1011 +
1$
#600
0$
#610
1!
b1111 ,
b111 "
b111 (
b111 +
1$
#620
0$
#630
0!
b1110 ,
b1111 "
b1111 (
b1111 +
1$
#640
0$
#650
b1100 ,
b1110 "
b1110 (
b1110 +
1$
#660
0$
#670
b1000 ,
b1100 "
b1100 (
b1100 +
1$
#680
0$
#685
b100 -
