Lab1/fulladder/fulladder_dataflow.sv
// FullAdder gate level code
module fulladder(
  input logic a, b, cin, 
  output logic sum, cout
);
  logic p, q;  
  assign p = a ^ b;
  assign q = a & b;
  assign sum = p ^ cin;
  assign cout = q | (p & cin);
endmodule

Homework6/carry_lookahead_adder/carry_lookahead_adder.sv
// `include "fulladder.sv"
module carry_lookahead_adder#(parameter N=4)(
  input logic[N-1:0] A, B,
  input logic CIN,
  output logic[N:0] result
);

logic[N:0] myresult;
logic[N-1:0] myCIN;
logic lastcout;


always_comb begin
  myCIN[0] = CIN;
  myCIN[1] = (A[0]&B[0]) | ((A[0]|B[0])&myCIN[0]);
  myCIN[2] = (A[1]&B[1]) | ((A[1]|B[1])&myCIN[1]);
  myCIN[3] = (A[2]&B[2]) | ((A[2]|B[2])&myCIN[2]);
  // $display("%b",myCIN);
end

fulladder FA0 (.a(A[0]), .b(B[0]), .cin(myCIN[0]), .sum(myresult[0]));
fulladder FA1 (.a(A[1]), .b(B[1]), .cin(myCIN[1]), .sum(myresult[1]));
fulladder FA2 (.a(A[2]), .b(B[2]), .cin(myCIN[2]), .sum(myresult[2]));
fulladder FA3 (.a(A[3]), .b(B[3]), .cin(myCIN[3]), .sum(myresult[3]), .cout(lastcout));

assign myresult[4] = lastcout;
assign result = myresult;

  
endmodule: carry_lookahead_adder

Homework6/carry_lookahead_adder/carry_lookahead_adder_testbench.sv
`timescale 1ns/1ns
//Carry Lookahead Adder Testbench Code
module carry_lookahead_adder_testbench;
 parameter N = 4;
 logic[N-1:0] in0, in1;
 logic carryin;
 logic[N:0] sum;

// Instantiate design under test
carry_lookahead_adder #(.N(N)) design_instance(
.A(in0),
.B(in1),
.CIN(carryin),
.result(sum)
);

initial begin
// Initialize Inputs
in0=0;
in1=0;
carryin=0;
// Wait 100 ns 
#100;
in0=2;
in1=1;
carryin=1;
#50 
in0=1;
in1=1;
carryin=0;
#50
in0=2;
in1=2;
carryin=0;
#50
in0=3;
in1=1;
carryin=0;
#50; 
in0=4;
in1=7;
carryin=1;
#50; 
in0=15;
in1=2;
carryin=0;
#50;
in0=10;
in1=5;
carryin=0;
#50;
end


// always@(in0) begin
//     #1;
//     $display(" time=%0t   A=%b   B=%b   CIN=%b   result=%b\n", $time, in0, in1, carryin, sum);
// end
initial begin
 $monitor(" time=%0t   A=%b   B=%b   CIN=%b   result=%b\n", $time, in0, in1, carryin, sum);
end

initial begin
	$dumpfile("dump.vcd.tmp");
	$dumpvars;
end
endmodule

Homework6/carry_lookahead_adder/carry_lookahead_adder.vcd
$date
	Sat Feb 17 22:16:15 2024
$end
$version
	Icarus Verilog
$end
$timescale
	1ns
$end
$scope module carry_lookahead_adder_testbench $end
$var wire 5 ! sum [4:0] $end
$var parameter 32 " N $end
$var reg 1 # carryin $end
$var reg 4 $ in0 [3:0] $end
$var reg 4 % in1 [3:0] $end
$scope module design_instance $end
$var wire 4 & A [3:0] $end
$var wire 4 ' B [3:0] $end
$var wire 1 # CIN $end
$var wire 5 ( result [4:0] $end
$var wire 5 ) myresult [4:0] $end
$var wire 1 * lastcout $end
$var parameter 32 + N $end
$var reg 4 , myCIN [3:0] $end
$scope module FA0 $end
$var wire 1 - a $end
$var wire 1 . b $end
$var wire 1 / cin $end
$var wire 1 0 cout $end
$var wire 1 1 p $end
$var wire 1 2 q $end
$var wire 1 3 sum $end
$upscope $end
$scope module FA1 $end
$var wire 1 4 a $end
$var wire 1 5 b $end
$var wire 1 6 cin $end
$var wire 1 7 cout $end
$var wire 1 8 p $end
$var wire 1 9 q $end
$var wire 1 : sum $end
$upscope $end
$scope module FA2 $end
$var wire 1 ; a $end
$var wire 1 < b $end
$var wire 1 = cin $end
$var wire 1 > cout $end
$var wire 1 ? p $end
$var wire 1 @ q $end
$var wire 1 A sum $end
$upscope $end
$scope module FA3 $end
$var wire 1 B a $end
$var wire 1 C b $end
$var wire 1 D cin $end
$var wire 1 * cout $end
$var wire 1 E p $end
$var wire 1 F q $end
$var wire 1 G sum $end
$upscope $end
$upscope $end
$upscope $end
$enddefinitions $end
$comment Show the parameter values. $end
$dumpall
b100 +
b100 "
$end
#0
$dumpvars
0G
0F
0E
0D
0C
0B
0A
0@
0?
0>
0=
0<
0;
0:
09
08
07
06
05
04
03
02
01
00
0/
0.
0-
b0 ,
0*
b0 )
b0 (
b0 '
b0 &
b0 %
b0 $
0#
b0 !
$end
#100
10
17
b100 !
b100 (
b100 )
1A
11
1=
16
1/
18
1.
b111 ,
14
1#
b1 %
b1 '
b10 $
b10 &
#150
07
0A
b10 !
b10 (
b10 )
1:
0=
0/
01
12
08
b10 ,
1-
04
0#
b1 $
b1 &
#200
1A
b100 !
b100 (
b100 )
0:
00
17
1=
06
02
19
0.
15
b100 ,
0-
14
b10 %
b10 '
b10 $
b10 &
#250
10
18
09
16
12
1.
05
b110 ,
1-
b1 %
b1 '
b11 $
b11 &
#300
b1100 !
b1100 (
b1100 )
1G
10
1>
1D
1/
11
02
1@
15
1<
b1111 ,
0-
04
1;
1#
b111 %
b111 '
b100 $
b100 &
#350
00
1*
0A
1>
13
b10001 !
b10001 (
b10001 )
0G
1?
0@
06
0/
08
19
1E
0.
0<
b1100 ,
1-
14
1B
0#
b10 %
b10 '
b1111 $
b1111 &
#400
0*
0>
1:
07
1G
b1111 !
b1111 (
b1111 )
1A
18
09
0D
0=
1.
05
1<
b0 ,
0-
0;
b101 %
b101 '
b1010 $
b1010 &
