Homework7/conv_enc.sv
// rate 1/2 convolutional encoder with programmable taps and length
// bitwise row of AND gates makes feedback pattern programmable
// N = 1 + constraint length
module conv_enc #(parameter N = 6)( // N = shift reg. length
  input        clk, data_in, reset,
  input  [1:0] load_mask,  // 1: load mask0 pattern; 2: load mask1 
  input  [N-1:0] mask,       // mask pattern to be loaded; prepend with 1  
  output logic[1:0] data_out    // encoded data out
);  

logic [N-1:0] shift_reg, mask_a, mask_b;

always_ff @(posedge clk, negedge reset) begin // This should be shift register code
  if (!reset) 
    shift_reg <= {N{1'b0}};
  else 
    if (load_mask == 2'b00)
      shift_reg <= {data_in, shift_reg[N-1:1]}; // According to testbench it should be MSB on the left
end

always_ff @(posedge clk) begin // Check for loading on the posedge of every clock
  if (load_mask == 2'b01)
    mask_a <= mask;
  if (load_mask == 2'b10)
    mask_b <= mask;
end

always_comb begin
  data_out[0] = ^(mask_a & shift_reg);
  data_out[1] = ^(mask_b & shift_reg);
end

endmodule

Homework7/conv_enc_tb.sv
`timescale 1ns/1ns // testbench code is missing this??? Without it fails

module conv_enc_tb;
  parameter N = 4;                  // set to desired constraint length + 1;
  bit          clk, data_in, reset;
  bit  [  1:0] load_mask;		      // 01: load mask 0; 10: load mask 1
  bit  [N-1:0] mask, mask0, mask1,   // prepend desired mask vaue with 1
              histo;
  logic[  1:0] data_outP;
  wire [  1:0] data_out;			  // assumes rate 1/2

  // rate 1/2, constraint N-1 convolutional encoder
  conv_enc #(.N(N)) ce1(.clk,
              .data_in,
        .reset,
        .load_mask,
        .mask,
        .data_out);

always begin
  #5ns clk = 1'b1;
  #5ns clk = 1'b0;
end

always @(posedge clk)               // histo = "history"
  histo <= {data_in,histo[N-1:1]};	// just a shift register

always @(negedge clk)
  if(data_outP == data_out)
    $display("expected %b, got %b  YAA!",data_outP,data_out);
  else
    $display("expected %b, got %b  DAMN!",data_outP,data_out);

initial begin
  clk = 0; // Initialize clock
  #10ns mask      =  'o17;//'o15;		  // 5 with 1 prepended
        mask0     =  mask;
  #10ns load_mask = 2'b01;
  #10ns load_mask = 2'b00;
  #10ns mask      =  'o13;//'o17;
        mask1     =  mask;
  #10ns load_mask = 2'b10;
  #10ns load_mask = 2'b00;
  #10ns reset     = 1'b1;		  // start running
  #10ns data_in   = 1'b0;		  // sequence from Viterbi demo
  #90ns data_in   = 1'b1;
  // sequence from thesis
  #10ns data_in   = 1'b1;
  #10ns data_in   = 1'b0;
  #10ns data_in   = 1'b1;
  #10ns data_in   = 1'b0;
  #10ns data_in   = 1'b0;
  #10ns data_in   = 1'b0;
  #10ns data_in   = 1'b0;
  #10ns data_in   = 1'b0;
  #10ns data_in   = 1'b0;
  #10ns data_in   = 1'b0;
  #10ns data_in   = 1'b0;
  #10ns data_in   = 1'b0;
  #10ns data_in   = 1'b0;
    
  // #40ns $finish();
  #10ns data_in   = 1'b0;
  #10ns data_in   = 1'b1;
  #10ns data_in   = 1'b1;
  #10ns data_in   = 1'b0;
  // #40ns $finish(); 
  #40ns data_in   = 1'b1;
  #10ns data_in   = 1'b0;
  #10ns data_in   = 1'b1;
  #10ns data_in   = 1'b1;
  #10ns data_in   = 1'b0;
  #10ns data_in   = 1'b0;
  #10ns data_in   = 1'b0;
  #10ns data_in   = 1'b0;
  #10ns data_in   = 1'b0;
  #10ns data_in   = 1'b0;
  #10ns data_in   = 1'b0;
  #10ns data_in   = 1'b0;
  // #10ns $finish(); 
  #40ns data_in   = 1'b1;
  #10ns data_in   = 1'b0;
  #10ns data_in   = 1'b1;
  #10ns data_in   = 1'b1;
  #10ns data_in   = 1'b1;
  #10ns data_in   = 1'b0;
  #10ns data_in   = 1'b0;
  // #40ns $finish(); 
  #10ns data_in   = 1'b1;
  #10ns data_in   = 1'b0;
  #10ns data_in   = 1'b1;
  #10ns data_in   = 1'b0;
  #10ns data_in   = 1'b0;
  #10ns data_in   = 1'b0;
  #10ns data_in   = 1'b1;
  #10ns data_in   = 1'b0;
  #60ns $finish();
end

always_comb begin
  data_outP[1] = ^(mask1&histo);
  data_outP[0] = ^(mask0&histo);
end

initial begin
	$dumpfile("dump.vcd.tmp");
	$dumpvars;
end

endmodule

Homework7/conv_enc.vcd
$date
	Sat Feb 24 10:28:18 2024
$end
$version
	Icarus Verilog
$end
$timescale
	1ns
$end
$scope module conv_enc_tb $end
$var wire 2 ! data_out [1:0] $end
$var parameter 32 " N $end
$var reg 2 # data_outP [1:0] $end
$var reg 1 $ clk $end
$var reg 1 % data_in $end
$var reg 4 & histo [3:0] $end
$var reg 2 ' load_mask [1:0] $end
$var reg 4 ( mask [3:0] $end
$var reg 4 ) mask0 [3:0] $end
$var reg 4 * mask1 [3:0] $end
$var reg 1 + reset $end
$scope module ce1 $end
$var wire 1 $ clk $end
$var wire 1 % data_in $end
$var wire 2 , load_mask [1:0] $end
$var wire 4 - mask [3:0] $end
$var wire 1 + reset $end
$var parameter 32 . N $end
$var reg 2 / data_out [1:0] $end
$var reg 4 0 mask_a [3:0] $end
$var reg 4 1 mask_b [3:0] $end
$var reg 4 2 shift_reg [3:0] $end
$upscope $end
$upscope $end
$enddefinitions $end
$comment Show the parameter values. $end
$dumpall
b100 .
b100 "
$end
#0
$dumpvars
bx 2
bx 1
bx 0
bx /
b0 -
b0 ,
0+
b0 *
b0 )
b0 (
b0 '
b0 &
0%
0$
b0 #
bx !
$end
#5
b0 !
b0 /
b0 2
1$
#10
0$
b1111 )
b1111 (
b1111 -
#15
1$
#20
0$
b1 '
b1 ,
#25
b1111 0
1$
#30
0$
b0 '
b0 ,
#35
1$
#40
0$
b1011 *
b1011 (
b1011 -
#45
1$
#50
0$
b10 '
b10 ,
#55
b1011 1
1$
#60
0$
b0 '
b0 ,
#65
1$
#70
0$
1+
#75
1$
#80
0$
#85
1$
#90
0$
#95
1$
#100
0$
#105
1$
#110
0$
#115
1$
#120
0$
#125
1$
#130
0$
#135
1$
#140
0$
#145
1$
#150
0$
#155
1$
#160
0$
#165
1$
#170
0$
1%
#175
b11 #
b11 !
b11 /
b1000 &
b1000 2
1$
#180
0$
#185
b10 #
b10 !
b10 /
b1100 &
b1100 2
1$
#190
0$
0%
#195
b110 &
b110 2
1$
#200
0$
1%
#205
b11 #
b11 !
b11 /
b1011 &
b1011 2
1$
#210
0$
0%
#215
b10 #
b10 !
b10 /
b101 &
b101 2
1$
#220
0$
#225
b11 #
b11 !
b11 /
b10 &
b10 2
1$
#230
0$
#235
b1 &
b1 2
1$
#240
0$
#245
b0 #
b0 !
b0 /
b0 &
b0 2
1$
#250
0$
#255
1$
#260
0$
#265
1$
#270
0$
#275
1$
#280
0$
#285
1$
#290
0$
#295
1$
#300
0$
#305
1$
#310
0$
#315
1$
#320
0$
1%
#325
b11 #
b11 !
b11 /
b1000 &
b1000 2
1$
#330
0$
#335
b10 #
b10 !
b10 /
b1100 &
b1100 2
1$
#340
0$
0%
#345
b110 &
b110 2
1$
#350
0$
#355
b0 #
b0 !
b0 /
b11 &
b11 2
1$
#360
0$
#365
b11 #
b11 !
b11 /
b1 &
b1 2
1$
#370
0$
#375
b0 #
b0 !
b0 /
b0 &
b0 2
1$
#380
0$
1%
#385
b11 #
b11 !
b11 /
b1000 &
b1000 2
1$
#390
0$
0%
#395
b1 #
b1 !
b1 /
b100 &
b100 2
1$
#400
0$
1%
#405
b0 #
b0 !
b0 /
b1010 &
b1010 2
1$
#410
0$
#415
b1 #
b1 !
b1 /
b1101 &
b1101 2
1$
#420
0$
0%
#425
b10 #
b10 !
b10 /
b110 &
b110 2
1$
#430
0$
#435
b0 #
b0 !
b0 /
b11 &
b11 2
1$
#440
0$
#445
b11 #
b11 !
b11 /
b1 &
b1 2
1$
#450
0$
#455
b0 #
b0 !
b0 /
b0 &
b0 2
1$
#460
0$
#465
1$
#470
0$
#475
1$
#480
0$
#485
1$
#490
0$
#495
1$
#500
0$
#505
1$
#510
0$
#515
1$
#520
0$
#525
1$
#530
0$
1%
#535
b11 #
b11 !
b11 /
b1000 &
b1000 2
1$
#540
0$
0%
#545
b1 #
b1 !
b1 /
b100 &
b100 2
1$
#550
0$
1%
#555
b0 #
b0 !
b0 /
b1010 &
b1010 2
1$
#560
0$
#565
b1 #
b1 !
b1 /
b1101 &
b1101 2
1$
#570
0$
#575
b1110 &
b1110 2
1$
#580
0$
0%
#585
b111 &
b111 2
1$
#590
0$
#595
b0 #
b0 !
b0 /
b11 &
b11 2
1$
#600
0$
1%
#605
b1001 &
b1001 2
1$
#610
0$
0%
#615
b1 #
b1 !
b1 /
b100 &
b100 2
1$
#620
0$
1%
#625
b0 #
b0 !
b0 /
b1010 &
b1010 2
1$
#630
0$
0%
#635
b10 #
b10 !
b10 /
b101 &
b101 2
1$
#640
0$
#645
b11 #
b11 !
b11 /
b10 &
b10 2
1$
#650
0$
#655
b1 &
b1 2
1$
#660
0$
1%
#665
b1000 &
b1000 2
1$
#670
0$
0%
#675
b1 #
b1 !
b1 /
b100 &
b100 2
1$
#680
0$
#685
b11 #
b11 !
b11 /
b10 &
b10 2
1$
#690
0$
#695
b1 &
b1 2
1$
#700
0$
#705
b0 #
b0 !
b0 /
b0 &
b0 2
1$
