Homework8/design/uart_rx.sv
// UART RX RTL Code
module uart_rx #(parameter NUM_CLKS_PER_BIT=16)
(input logic clk, rstn,  
 input logic rx, // input serial incoming data
 output logic done, // indicates 8-bit serial data is converted into 8-bit parallel data and available on dout port
 output logic [7:0] dout // 8-bit parallel data output
);
 
// count variable
logic [$clog2(NUM_CLKS_PER_BIT)-1:0] count;

// state encoding and state variable
enum logic[3:0]{
  RX_IDLE       = 4'b0000,
  RX_START_BIT  = 4'b0001,
  RX_DATA_BIT0  = 4'b0010,
  RX_DATA_BIT1  = 4'b0011,
  RX_DATA_BIT2  = 4'b0100,
  RX_DATA_BIT3  = 4'b0101,
  RX_DATA_BIT4  = 4'b0110,
  RX_DATA_BIT5  = 4'b0111,
  RX_DATA_BIT6  = 4'b1000,
  RX_DATA_BIT7  = 4'b1001,
  RX_STOP_BIT   = 4'b1010} state;

always_ff@(posedge clk) begin
  // $display("dout = %b rx = %b state =%s", dout, rx, state.name());
  if(!rstn) begin
    done <= 0;
    count <= 0;
    dout <= 0;
    state <= RX_IDLE;
  end
  else begin
    case(state)
      RX_IDLE: begin
        done <= 0;
        count <= 0;
        dout <= dout;
        // Wait for rx = 0 indicating start bit
        if(rx == 0) state <= RX_START_BIT;
        else state <= RX_IDLE;
      end
      RX_START_BIT: begin
        // sample start bit value at mid-point, for start bit counter
        // value = 7 is midpoint
        // wait for rx to transition from 1 to 0
        if(rx == 0 && count == ((NUM_CLKS_PER_BIT-1)/2)) begin
            done <= 0;
            state <= RX_DATA_BIT0;
            count <= 0;
            dout <= {rx, dout[7:1]};
        end else begin
            count <= count + 1;
        end
      end
      RX_DATA_BIT0: begin
        if(count == NUM_CLKS_PER_BIT-1) begin
          done <= 0;
          state <= RX_DATA_BIT1;
          count <= 0;
          dout <= {rx, dout[7:1]};
        end else begin
          count <= count + 1;
        end
      end
      RX_DATA_BIT1: begin
        if(count == NUM_CLKS_PER_BIT-1) begin
          done <= 0;
          state <= RX_DATA_BIT2;
          count <= 0;
          dout <= {rx, dout[7:1]};
        end else begin
          count <= count + 1;
        end
      end
      RX_DATA_BIT2: begin
        if(count == NUM_CLKS_PER_BIT-1) begin
          done <= 0;
          state <= RX_DATA_BIT3;
          count <= 0;
          dout <= {rx, dout[7:1]};
        end else begin
          count <= count + 1;
        end
      end
      RX_DATA_BIT3: begin
        if(count == NUM_CLKS_PER_BIT-1) begin
          done <= 0;
          state <= RX_DATA_BIT4;
          count <= 0;
          dout <= {rx, dout[7:1]};
        end else begin
          count <= count + 1;
        end
      end
      RX_DATA_BIT4: begin
        if(count == NUM_CLKS_PER_BIT-1) begin
          done <= 0;
          state <= RX_DATA_BIT5;
          count <= 0;
          dout <= {rx, dout[7:1]};
        end else begin
          count <= count + 1;
        end
      end
      RX_DATA_BIT5: begin
        if(count == NUM_CLKS_PER_BIT-1) begin
          done <= 0;
          state <= RX_DATA_BIT6;
          count <= 0;
          dout <= {rx, dout[7:1]};
        end else begin
          count <= count + 1;
        end
      end
      RX_DATA_BIT6: begin
        if(count == NUM_CLKS_PER_BIT-1) begin
          done <= 0;
          state <= RX_DATA_BIT7;
          count <= 0;
          dout <= {rx, dout[7:1]};
        end else begin
          count <= count + 1;
        end
      end
      RX_DATA_BIT7: begin
        if(count == NUM_CLKS_PER_BIT-1) begin
          done <= 0;
          state <= RX_STOP_BIT;
          count <= 0;
          dout <= {rx, dout[7:1]};
        end else begin
          count <= count + 1;
        end
      end
      RX_STOP_BIT: begin
        done <= 1;
        state <= RX_IDLE;
        count <= 0;
        // dout <= dout;
      end
            
    endcase
  end
end
endmodule: uart_rx


// sample start bit value at mid-point
// for each databit to get midpoint count value is 16
// counting starts from midpoint of previous bit and ends at midpoint
// of current data bit
// Student to fill rest of the code
// Student to fill rest of the code for all remaining data bits and stop bit

Homework8/design/uart_tx.sv
// UART TX RTL Code
module uart_tx #(parameter NUM_CLKS_PER_BIT=16)
(input logic clk, rstn,  
 input logic[7:0] din, // input parallel 8-bit data
 input logic start, // input start bit indicating new 8-bit data can be sampled by Uart Tx
 output logic done,// output done indidcates 8-bit parallel data is serially transmitted by Uart Tx
 output logic tx // serial 8-bit data output from uart tx
);

// count variable
logic [$clog2(NUM_CLKS_PER_BIT)-1:0] count;

// state encoding and state variable
enum logic[2:0]{
  TX_IDLE       = 3'b000,
  TX_START_BIT  = 3'b001,
  TX_DATA_BIT   = 3'b010,
  TX_STOP_BIT   = 3'b011,
  TX_CLEANUP    = 3'b100} state;

// data index bit
logic [2:0] bit_index;

// UART TX Format
// TX_START_BIT -> 8 DATA_BITS Transmitted one at at time -> STOP_BIT
// TX_SART_BIT is 0 (1 to 0 transition is detected as start bit)
// TX_STOP_BIT is 1

// FSM with single always block for next state, 
// present state flipflop and output logic 
always_ff@(posedge clk) begin
	if(!rstn) begin
		count <= 0;
		state <= TX_IDLE;
		bit_index <= 0;
		tx <= 0;
		done <= 0;
	end
 	else begin
		case(state)
			TX_IDLE: begin
				count <= 0;						
				tx <= 1; // Output tx = 1 indicates stop state
				done <= 0;
				bit_index <= 0; // If start is set to '1' then start sampling UART Tx packet START BIT from next cycle
				if(rstn==1 && start == 1) state <= TX_START_BIT;
				else state<= TX_IDLE;
			end
			TX_START_BIT: begin	
				tx<=0;   // Output rx = 0 indicates as start bit
				done <= 0;
				bit_index <= 0; // Transmit START BIT for NUM_CLKS_PER_BIT period
				if(count == (NUM_CLKS_PER_BIT-1)) begin
					state <= TX_DATA_BIT;
					count <= 0;
				end else begin
					state <= TX_START_BIT;
					count <= count + 1;
				end
			end
			TX_DATA_BIT: begin
				tx <= din[bit_index];
				done <= 0;
				// Transmit START BIT for NUM_CLKS_PER_BIT period
				if(count == (NUM_CLKS_PER_BIT-1)) begin
					count <= 0;
					// Check if all 8 data bits are transmitted
					if(bit_index == 7) begin
						bit_index <= 0;
						state <= TX_STOP_BIT;
					end
					else begin
						bit_index <= bit_index + 1;
						state <= TX_DATA_BIT;
					end
				end
				else begin 
					state <= TX_DATA_BIT; 
					count <= count + 1;
				end
			end
			TX_STOP_BIT: begin
				tx <= 1;
				bit_index <= 0;
					// Transmit STOP BIT for NUM_CLKS_PER_BIT period
				if(count == (NUM_CLKS_PER_BIT-1)) begin
					state <= TX_CLEANUP;
					count <= 0;
					// 8 paralle data bits into serial data bits and 
					// available on output tx signal
					done <= 1; // Generate Done=1 which indicates that UART TX has converted 
				end else begin
					state <= TX_STOP_BIT;
					count <= count + 1;
				end
			end
			TX_CLEANUP: begin
				done <= 1; // Stay in this state for 1 clock cycle and keep done asserted for 1 cycle
				state <= TX_IDLE;		            
			end
			default: begin
				done <= 0;
				state <= TX_IDLE;
				tx <= 0;  		  
			end
		endcase
	end	
end
endmodule: uart_tx

Homework8/design/uart_top.sv
// UART TX RTL Code
module uart_top #(parameter NUM_CLKS_PER_BIT=16)
(input             tx_clk, tx_rstn, rx_clk, rx_rstn,  
 input [7:0]       tx_din,
 input             tx_start,
 output logic      tx_done, rx_done,
 output logic[7:0] rx_dout);


// wire to connect output of uart_tx "tx" signal to
// uart_rx "rx" signal
wire serial_data_bit;

// Instantiate uart transmitter module
// student to add code

uart_tx #(.NUM_CLKS_PER_BIT(NUM_CLKS_PER_BIT)) uart_tx_instance (
  .clk(tx_clk),
  .rstn(tx_rstn),
  .din(tx_din),
  .start(tx_start),
  .done(tx_done),
  .tx(serial_data_bit)
);

// Instantiate uart receiver module
// student to add code

uart_rx #(.NUM_CLKS_PER_BIT(NUM_CLKS_PER_BIT)) uart_rx_instasnce (
  .clk(rx_clk),
  .rstn(rx_rstn),
  .rx(serial_data_bit),
  .done(rx_done),
  .dout(rx_dout)
);

endmodule: uart_top

Homework8/test_benches/uart_top_testbench.sv
//UART TOP Testbench Code
`timescale 1ns/1ns
module uart_top_testbench;
// Uart Transmitter and Receiver clock frequency
// CLK_PERIOD_NS * 2 = 10 x 2 = 20ns
parameter CLK_PERIOD_NS = 10;

// Number of bits in UART packets
// 1 Start bit + 8 Data Bits + 1 Stop bit = 10
parameter NUM_SERIAL_BITS = 10;

// Number of clocks per bit will be used by 
// within uart transmitter and receiver.
// Witin Uart Tx, this will be used to transmit each serial bit
// for NUM_CLKS_PER_BIT count.
// Within Uart Rx, this will be used to find mid point of serial data bit
// and then sample data.
// NUM_CLKS_PER_BIT = Frequency / Baud Rate
// Frequency = 1 / (2 * CLK_PERIOD_NS)
// Example : for Frequency 50 Mhz, Baud Rate = 115200
// NUM_CLKS_PER_BIT = (50 x 10^6) / 115200 = 434
// parameter NUM_CLKS_PER_BIT = 434;
parameter NUM_CLKS_PER_BIT = 62;  // for faster simulation and easy debug setting value to 16 instead of 434

// Only required for testbench for allowing 10 bits parallel
// data getting converted and transmitted serially on rx signal
// from uart receiver. Between two din packets injected by testbench
// into uart tx, this will be used as a delay
parameter TRANSMIT_TIME = (NUM_CLKS_PER_BIT * (CLK_PERIOD_NS*2) * NUM_SERIAL_BITS);

// local variable
bit clock_tx, clock_rx, clock_by_n, rstn;
bit start;
wire done, ready;
bit [7:0] din;
wire[7:0] dout;
logic[7:0] byte_data;
//logic[7:0] byte_data[int];
int index;

// Instantiate design under test
uart_top #(.NUM_CLKS_PER_BIT(NUM_CLKS_PER_BIT)) DUT(
.tx_clk(clock_tx),
.tx_rstn(rstn),
.rx_clk(clock_rx),
.rx_rstn(rstn),
.tx_start(start),
.tx_done(done),
.tx_din(din),
.rx_done(ready),
.rx_dout(dout)
);

initial begin

// Wait 20 ns for global reset to finish 
#20;
rstn = 1;
#20;

// Initialize 8-data to be transmitted
byte_data = 8'hA2;
for(integer i=0; i<4; i++) begin
 // wait for posedge of clock and then assign start = 1
 @(posedge clock_tx);
 start = 1;

 // wait for once cycle and then assign start = 0
 @(posedge clock_tx);
 start = 0;

 // create new 8-bit data packet
 byte_data = byte_data + 8'h3;	   //	 $random;

 // assign uart tx input din, 8-bit generated datat
 din = byte_data;
           
//if (dout == byte_data)
// $display("Test Passed - Correct Byte Received time=%t  expected=%h   actual=%h", $time, byte_data, dout);
 //else
 // $display("Test Error- Incorrect Byte Received time=%t  expected=%h   actual=%h", $time, byte_data, dout);

 //#(BIT_PERIOD_NS);

 // wait until entire uart tx packet (10bits din) are
 // serially transmitted by uart transmitter
 // on its rx output signal before new uart packet
 // are injected into uart transmitter
 #TRANSMIT_TIME;

 // wait for uart transmitter to indicate to testbench
 // that entire 10-bits were transmitted, before new
 // uart packet is injected into uart transmitter
 @(negedge done);
end

// Wait & terminate
#500ns $finish;
end

// wait for ready signal to be asserted from
// uart receiver to capture parallel data
// out (dout) from uart receiver and compare with
// parallel 8bit data which was injected into 
// uart transmitter on din signal.
always@(posedge ready) begin
 // Check that the correct 8-bit parallel data was received at the output of uart rx on dout port 
 if (dout == byte_data)
  $display("Test Passed - Correct Byte Received time=%t  expected=%h   actual=%h", $time, byte_data, dout);
 else begin
  $error("Test Error- Incorrect Byte Received time=%t  expected=%h   actual=%h", $time, byte_data, dout);
  $finish;
 end
 index = index + 1; 
end

// Clock generator logic (used by both uart tx and uart rx modules)
always begin
  #CLK_PERIOD_NS clock_tx = 1'b1;
  #CLK_PERIOD_NS clock_tx = 1'b0;
end
always begin
  #CLK_PERIOD_NS clock_rx = 1'b1;
  #CLK_PERIOD_NS clock_rx = 1'b0;
end

initial begin
	$dumpfile("dump.vcd.tmp");
	$dumpvars;
end
endmodule

Homework8/uart_top.vcd
$date
	Sat Mar  2 11:49:11 2024
$end
$version
	Icarus Verilog
$end
$timescale
	1ns
$end
$scope module uart_top_testbench $end
$var wire 1 ! ready $end
$var wire 8 " dout [7:0] $end
$var wire 1 # done $end
$var parameter 32 $ CLK_PERIOD_NS $end
$var parameter 32 % NUM_CLKS_PER_BIT $end
$var parameter 32 & NUM_SERIAL_BITS $end
$var parameter 128 ' TRANSMIT_TIME $end
$var reg 8 ( byte_data [7:0] $end
$var reg 1 ) clock_rx $end
$var reg 1 * clock_tx $end
$var reg 8 + din [7:0] $end
$var integer 32 , index [31:0] $end
$var reg 1 - rstn $end
$var reg 1 . start $end
$scope module DUT $end
$var wire 1 ) rx_clk $end
$var wire 1 - rx_rstn $end
$var wire 1 * tx_clk $end
$var wire 8 / tx_din [7:0] $end
$var wire 1 - tx_rstn $end
$var wire 1 . tx_start $end
$var wire 1 # tx_done $end
$var wire 1 0 serial_data_bit $end
$var wire 8 1 rx_dout [7:0] $end
$var wire 1 ! rx_done $end
$var parameter 32 2 NUM_CLKS_PER_BIT $end
$scope module uart_rx_instasnce $end
$var wire 1 ) clk $end
$var wire 1 - rstn $end
$var wire 1 0 rx $end
$var parameter 32 3 NUM_CLKS_PER_BIT $end
$var reg 6 4 count [5:0] $end
$var reg 1 ! done $end
$var reg 8 5 dout [7:0] $end
$var reg 4 6 state [3:0] $end
$upscope $end
$scope module uart_tx_instance $end
$var wire 1 * clk $end
$var wire 8 7 din [7:0] $end
$var wire 1 - rstn $end
$var wire 1 . start $end
$var parameter 32 8 NUM_CLKS_PER_BIT $end
$var reg 3 9 bit_index [2:0] $end
$var reg 6 : count [5:0] $end
$var reg 1 # done $end
$var reg 3 ; state [2:0] $end
$var reg 1 0 tx $end
$upscope $end
$upscope $end
$scope begin $ivl_for_loop0 $end
$var integer 32 < i [31:0] $end
$upscope $end
$upscope $end
$enddefinitions $end
$comment Show the parameter values. $end
$dumpall
b111110 8
b111110 3
b111110 2
b11000001110000 '
b1010 &
b111110 %
b1010 $
$end
#0
$dumpvars
bx <
bx ;
bx :
bx 9
b0 7
bx 6
bx 5
bx 4
bx 1
x0
b0 /
0.
0-
b0 ,
b0 +
0*
0)
bx (
x#
bx "
x!
$end
#10
b0 6
b0 "
b0 1
b0 5
b0 4
0!
0#
00
b0 9
b0 ;
b0 :
1)
1*
#20
0)
0*
1-
#30
b1 6
10
1)
1*
#40
0)
0*
b0 <
b10100010 (
#50
b1 4
b1 ;
1.
1)
1*
#60
0)
0*
#70
b10 4
b1 :
00
b10100101 +
b10100101 /
b10100101 7
b10100101 (
0.
1)
1*
#80
0)
0*
#90
b11 4
b10 :
1)
1*
#100
0)
0*
#110
b100 4
b11 :
1)
1*
#120
0)
0*
#130
b101 4
b100 :
1)
1*
#140
0)
0*
#150
b110 4
b101 :
1)
1*
#160
0)
0*
#170
b111 4
b110 :
1)
1*
#180
0)
0*
#190
b1000 4
b111 :
1)
1*
#200
0)
0*
#210
b1001 4
b1000 :
1)
1*
#220
0)
0*
#230
b1010 4
b1001 :
1)
1*
#240
0)
0*
#250
b1011 4
b1010 :
1)
1*
#260
0)
0*
#270
b1100 4
b1011 :
1)
1*
#280
0)
0*
#290
b1101 4
b1100 :
1)
1*
#300
0)
0*
#310
b1110 4
b1101 :
1)
1*
#320
0)
0*
#330
b1111 4
b1110 :
1)
1*
#340
0)
0*
#350
b10000 4
b1111 :
1)
1*
#360
0)
0*
#370
b10001 4
b10000 :
1)
1*
#380
0)
0*
#390
b10010 4
b10001 :
1)
1*
#400
0)
0*
#410
b10011 4
b10010 :
1)
1*
#420
0)
0*
#430
b10100 4
b10011 :
1)
1*
#440
0)
0*
#450
b10101 4
b10100 :
1)
1*
#460
0)
0*
#470
b10110 4
b10101 :
1)
1*
#480
0)
0*
#490
b10111 4
b10110 :
1)
1*
#500
0)
0*
#510
b11000 4
b10111 :
1)
1*
#520
0)
0*
#530
b11001 4
b11000 :
1)
1*
#540
0)
0*
#550
b11010 4
b11001 :
1)
1*
#560
0)
0*
#570
b11011 4
b11010 :
1)
1*
#580
0)
0*
#590
b11100 4
b11011 :
1)
1*
#600
0)
0*
#610
b11101 4
b11100 :
1)
1*
#620
0)
0*
#630
b11110 4
b11101 :
1)
1*
#640
0)
0*
#650
b0 4
b10 6
b11110 :
1)
1*
#660
0)
0*
#670
b1 4
b11111 :
1)
1*
#680
0)
0*
#690
b10 4
b100000 :
1)
1*
#700
0)
0*
#710
b11 4
b100001 :
1)
1*
#720
0)
0*
#730
b100 4
b100010 :
1)
1*
#740
0)
0*
#750
b101 4
b100011 :
1)
1*
#760
0)
0*
#770
b110 4
b100100 :
1)
1*
#780
0)
0*
#790
b111 4
b100101 :
1)
1*
#800
0)
0*
#810
b1000 4
b100110 :
1)
1*
#820
0)
0*
#830
b1001 4
b100111 :
1)
1*
#840
0)
0*
#850
b1010 4
b101000 :
1)
1*
#860
0)
0*
#870
b1011 4
b101001 :
1)
1*
#880
0)
0*
#890
b1100 4
b101010 :
1)
1*
#900
0)
0*
#910
b1101 4
b101011 :
1)
1*
#920
0)
0*
#930
b1110 4
b101100 :
1)
1*
#940
0)
0*
#950
b1111 4
b101101 :
1)
1*
#960
0)
0*
#970
b10000 4
b101110 :
1)
1*
#980
0)
0*
#990
b10001 4
b101111 :
1)
1*
#1000
0)
0*
#1010
b10010 4
b110000 :
1)
1*
#1020
0)
0*
#1030
b10011 4
b110001 :
1)
1*
#1040
0)
0*
#1050
b10100 4
b110010 :
1)
1*
#1060
0)
0*
#1070
b10101 4
b110011 :
1)
1*
#1080
0)
0*
#1090
b10110 4
b110100 :
1)
1*
#1100
0)
0*
#1110
b10111 4
b110101 :
1)
1*
#1120
0)
0*
#1130
b11000 4
b110110 :
1)
1*
#1140
0)
0*
#1150
b11001 4
b110111 :
1)
1*
#1160
0)
0*
#1170
b11010 4
b111000 :
1)
1*
#1180
0)
0*
#1190
b11011 4
b111001 :
1)
1*
#1200
0)
0*
#1210
b11100 4
b111010 :
1)
1*
#1220
0)
0*
#1230
b11101 4
b111011 :
1)
1*
#1240
0)
0*
#1250
b11110 4
b111100 :
1)
1*
#1260
0)
0*
#1270
b11111 4
b111101 :
1)
1*
#1280
0)
0*
#1290
b100000 4
b0 :
b10 ;
1)
1*
#1300
0)
0*
#1310
b100001 4
b1 :
10
1)
1*
#1320
0)
0*
#1330
b100010 4
b10 :
1)
1*
#1340
0)
0*
#1350
b100011 4
b11 :
1)
1*
#1360
0)
0*
#1370
b100100 4
b100 :
1)
1*
#1380
0)
0*
#1390
b100101 4
b101 :
1)
1*
#1400
0)
0*
#1410
b100110 4
b110 :
1)
1*
#1420
0)
0*
#1430
b100111 4
b111 :
1)
1*
#1440
0)
0*
#1450
b101000 4
b1000 :
1)
1*
#1460
0)
0*
#1470
b101001 4
b1001 :
1)
1*
#1480
0)
0*
#1490
b101010 4
b1010 :
1)
1*
#1500
0)
0*
#1510
b101011 4
b1011 :
1)
1*
#1520
0)
0*
#1530
b101100 4
b1100 :
1)
1*
#1540
0)
0*
#1550
b101101 4
b1101 :
1)
1*
#1560
0)
0*
#1570
b101110 4
b1110 :
1)
1*
#1580
0)
0*
#1590
b101111 4
b1111 :
1)
1*
#1600
0)
0*
#1610
b110000 4
b10000 :
1)
1*
#1620
0)
0*
#1630
b110001 4
b10001 :
1)
1*
#1640
0)
0*
#1650
b110010 4
b10010 :
1)
1*
#1660
0)
0*
#1670
b110011 4
b10011 :
1)
1*
#1680
0)
0*
#1690
b110100 4
b10100 :
1)
1*
#1700
0)
0*
#1710
b110101 4
b10101 :
1)
1*
#1720
0)
0*
#1730
b110110 4
b10110 :
1)
1*
#1740
0)
0*
#1750
b110111 4
b10111 :
1)
1*
#1760
0)
0*
#1770
b111000 4
b11000 :
1)
1*
#1780
0)
0*
#1790
b111001 4
b11001 :
1)
1*
#1800
0)
0*
#1810
b111010 4
b11010 :
1)
1*
#1820
0)
0*
#1830
b111011 4
b11011 :
1)
1*
#1840
0)
0*
#1850
b111100 4
b11100 :
1)
1*
#1860
0)
0*
#1870
b111101 4
b11101 :
1)
1*
#1880
0)
0*
#1890
b10000000 "
b10000000 1
b10000000 5
b0 4
b11 6
b11110 :
1)
1*
#1900
0)
0*
#1910
b1 4
b11111 :
1)
1*
#1920
0)
0*
#1930
b10 4
b100000 :
1)
1*
#1940
0)
0*
#1950
b11 4
b100001 :
1)
1*
#1960
0)
0*
#1970
b100 4
b100010 :
1)
1*
#1980
0)
0*
#1990
b101 4
b100011 :
1)
1*
#2000
0)
0*
#2010
b110 4
b100100 :
1)
1*
#2020
0)
0*
#2030
b111 4
b100101 :
1)
1*
#2040
0)
0*
#2050
b1000 4
b100110 :
1)
1*
#2060
0)
0*
#2070
b1001 4
b100111 :
1)
1*
#2080
0)
0*
#2090
b1010 4
b101000 :
1)
1*
#2100
0)
0*
#2110
b1011 4
b101001 :
1)
1*
#2120
0)
0*
#2130
b1100 4
b101010 :
1)
1*
#2140
0)
0*
#2150
b1101 4
b101011 :
1)
1*
#2160
0)
0*
#2170
b1110 4
b101100 :
1)
1*
#2180
0)
0*
#2190
b1111 4
b101101 :
1)
1*
#2200
0)
0*
#2210
b10000 4
b101110 :
1)
1*
#2220
0)
0*
#2230
b10001 4
b101111 :
1)
1*
#2240
0)
0*
#2250
b10010 4
b110000 :
1)
1*
#2260
0)
0*
#2270
b10011 4
b110001 :
1)
1*
#2280
0)
0*
#2290
b10100 4
b110010 :
1)
1*
#2300
0)
0*
#2310
b10101 4
b110011 :
1)
1*
#2320
0)
0*
#2330
b10110 4
b110100 :
1)
1*
#2340
0)
0*
#2350
b10111 4
b110101 :
1)
1*
#2360
0)
0*
#2370
b11000 4
b110110 :
1)
1*
#2380
0)
0*
#2390
b11001 4
b110111 :
1)
1*
#2400
0)
0*
#2410
b11010 4
b111000 :
1)
1*
#2420
0)
0*
#2430
b11011 4
b111001 :
1)
1*
#2440
0)
0*
#2450
b11100 4
b111010 :
1)
1*
#2460
0)
0*
#2470
b11101 4
b111011 :
1)
1*
#2480
0)
0*
#2490
b11110 4
b111100 :
1)
1*
#2500
0)
0*
#2510
b11111 4
b111101 :
1)
1*
#2520
0)
0*
#2530
b100000 4
b1 9
b0 :
1)
1*
#2540
0)
0*
#2550
b100001 4
b1 :
00
1)
1*
#2560
0)
0*
#2570
b100010 4
b10 :
1)
1*
#2580
0)
0*
#2590
b100011 4
b11 :
1)
1*
#2600
0)
0*
#2610
b100100 4
b100 :
1)
1*
#2620
0)
0*
#2630
b100101 4
b101 :
1)
1*
#2640
0)
0*
#2650
b100110 4
b110 :
1)
1*
#2660
0)
0*
#2670
b100111 4
b111 :
1)
1*
#2680
0)
0*
#2690
b101000 4
b1000 :
1)
1*
#2700
0)
0*
#2710
b101001 4
b1001 :
1)
1*
#2720
0)
0*
#2730
b101010 4
b1010 :
1)
1*
#2740
0)
0*
#2750
b101011 4
b1011 :
1)
1*
#2760
0)
0*
#2770
b101100 4
b1100 :
1)
1*
#2780
0)
0*
#2790
b101101 4
b1101 :
1)
1*
#2800
0)
0*
#2810
b101110 4
b1110 :
1)
1*
#2820
0)
0*
#2830
b101111 4
b1111 :
1)
1*
#2840
0)
0*
#2850
b110000 4
b10000 :
1)
1*
#2860
0)
0*
#2870
b110001 4
b10001 :
1)
1*
#2880
0)
0*
#2890
b110010 4
b10010 :
1)
1*
#2900
0)
0*
#2910
b110011 4
b10011 :
1)
1*
#2920
0)
0*
#2930
b110100 4
b10100 :
1)
1*
#2940
0)
0*
#2950
b110101 4
b10101 :
1)
1*
#2960
0)
0*
#2970
b110110 4
b10110 :
1)
1*
#2980
0)
0*
#2990
b110111 4
b10111 :
1)
1*
#3000
0)
0*
#3010
b111000 4
b11000 :
1)
1*
#3020
0)
0*
#3030
b111001 4
b11001 :
1)
1*
#3040
0)
0*
#3050
b111010 4
b11010 :
1)
1*
#3060
0)
0*
#3070
b111011 4
b11011 :
1)
1*
#3080
0)
0*
#3090
b111100 4
b11100 :
1)
1*
#3100
0)
0*
#3110
b111101 4
b11101 :
1)
1*
#3120
0)
0*
#3130
b1000000 "
b1000000 1
b1000000 5
b0 4
b100 6
b11110 :
1)
1*
#3140
0)
0*
#3150
b1 4
b11111 :
1)
1*
#3160
0)
0*
#3170
b10 4
b100000 :
1)
1*
#3180
0)
0*
#3190
b11 4
b100001 :
1)
1*
#3200
0)
0*
#3210
b100 4
b100010 :
1)
1*
#3220
0)
0*
#3230
b101 4
b100011 :
1)
1*
#3240
0)
0*
#3250
b110 4
b100100 :
1)
1*
#3260
0)
0*
#3270
b111 4
b100101 :
1)
1*
#3280
0)
0*
#3290
b1000 4
b100110 :
1)
1*
#3300
0)
0*
#3310
b1001 4
b100111 :
1)
1*
#3320
0)
0*
#3330
b1010 4
b101000 :
1)
1*
#3340
0)
0*
#3350
b1011 4
b101001 :
1)
1*
#3360
0)
0*
#3370
b1100 4
b101010 :
1)
1*
#3380
0)
0*
#3390
b1101 4
b101011 :
1)
1*
#3400
0)
0*
#3410
b1110 4
b101100 :
1)
1*
#3420
0)
0*
#3430
b1111 4
b101101 :
1)
1*
#3440
0)
0*
#3450
b10000 4
b101110 :
1)
1*
#3460
0)
0*
#3470
b10001 4
b101111 :
1)
1*
#3480
0)
0*
#3490
b10010 4
b110000 :
1)
1*
#3500
0)
0*
#3510
b10011 4
b110001 :
1)
1*
#3520
0)
0*
#3530
b10100 4
b110010 :
1)
1*
#3540
0)
0*
#3550
b10101 4
b110011 :
1)
1*
#3560
0)
0*
#3570
b10110 4
b110100 :
1)
1*
#3580
0)
0*
#3590
b10111 4
b110101 :
1)
1*
#3600
0)
0*
#3610
b11000 4
b110110 :
1)
1*
#3620
0)
0*
#3630
b11001 4
b110111 :
1)
1*
#3640
0)
0*
#3650
b11010 4
b111000 :
1)
1*
#3660
0)
0*
#3670
b11011 4
b111001 :
1)
1*
#3680
0)
0*
#3690
b11100 4
b111010 :
1)
1*
#3700
0)
0*
#3710
b11101 4
b111011 :
1)
1*
#3720
0)
0*
#3730
b11110 4
b111100 :
1)
1*
#3740
0)
0*
#3750
b11111 4
b111101 :
1)
1*
#3760
0)
0*
#3770
b100000 4
b10 9
b0 :
1)
1*
#3780
0)
0*
#3790
b100001 4
b1 :
10
1)
1*
#3800
0)
0*
#3810
b100010 4
b10 :
1)
1*
#3820
0)
0*
#3830
b100011 4
b11 :
1)
1*
#3840
0)
0*
#3850
b100100 4
b100 :
1)
1*
#3860
0)
0*
#3870
b100101 4
b101 :
1)
1*
#3880
0)
0*
#3890
b100110 4
b110 :
1)
1*
#3900
0)
0*
#3910
b100111 4
b111 :
1)
1*
#3920
0)
0*
#3930
b101000 4
b1000 :
1)
1*
#3940
0)
0*
#3950
b101001 4
b1001 :
1)
1*
#3960
0)
0*
#3970
b101010 4
b1010 :
1)
1*
#3980
0)
0*
#3990
b101011 4
b1011 :
1)
1*
#4000
0)
0*
#4010
b101100 4
b1100 :
1)
1*
#4020
0)
0*
#4030
b101101 4
b1101 :
1)
1*
#4040
0)
0*
#4050
b101110 4
b1110 :
1)
1*
#4060
0)
0*
#4070
b101111 4
b1111 :
1)
1*
#4080
0)
0*
#4090
b110000 4
b10000 :
1)
1*
#4100
0)
0*
#4110
b110001 4
b10001 :
1)
1*
#4120
0)
0*
#4130
b110010 4
b10010 :
1)
1*
#4140
0)
0*
#4150
b110011 4
b10011 :
1)
1*
#4160
0)
0*
#4170
b110100 4
b10100 :
1)
1*
#4180
0)
0*
#4190
b110101 4
b10101 :
1)
1*
#4200
0)
0*
#4210
b110110 4
b10110 :
1)
1*
#4220
0)
0*
#4230
b110111 4
b10111 :
1)
1*
#4240
0)
0*
#4250
b111000 4
b11000 :
1)
1*
#4260
0)
0*
#4270
b111001 4
b11001 :
1)
1*
#4280
0)
0*
#4290
b111010 4
b11010 :
1)
1*
#4300
0)
0*
#4310
b111011 4
b11011 :
1)
1*
#4320
0)
0*
#4330
b111100 4
b11100 :
1)
1*
#4340
0)
0*
#4350
b111101 4
b11101 :
1)
1*
#4360
0)
0*
#4370
b10100000 "
b10100000 1
b10100000 5
b0 4
b101 6
b11110 :
1)
1*
#4380
0)
0*
#4390
b1 4
b11111 :
1)
1*
#4400
0)
0*
#4410
b10 4
b100000 :
1)
1*
#4420
0)
0*
#4430
b11 4
b100001 :
1)
1*
#4440
0)
0*
#4450
b100 4
b100010 :
1)
1*
#4460
0)
0*
#4470
b101 4
b100011 :
1)
1*
#4480
0)
0*
#4490
b110 4
b100100 :
1)
1*
#4500
0)
0*
#4510
b111 4
b100101 :
1)
1*
#4520
0)
0*
#4530
b1000 4
b100110 :
1)
1*
#4540
0)
0*
#4550
b1001 4
b100111 :
1)
1*
#4560
0)
0*
#4570
b1010 4
b101000 :
1)
1*
#4580
0)
0*
#4590
b1011 4
b101001 :
1)
1*
#4600
0)
0*
#4610
b1100 4
b101010 :
1)
1*
#4620
0)
0*
#4630
b1101 4
b101011 :
1)
1*
#4640
0)
0*
#4650
b1110 4
b101100 :
1)
1*
#4660
0)
0*
#4670
b1111 4
b101101 :
1)
1*
#4680
0)
0*
#4690
b10000 4
b101110 :
1)
1*
#4700
0)
0*
#4710
b10001 4
b101111 :
1)
1*
#4720
0)
0*
#4730
b10010 4
b110000 :
1)
1*
#4740
0)
0*
#4750
b10011 4
b110001 :
1)
1*
#4760
0)
0*
#4770
b10100 4
b110010 :
1)
1*
#4780
0)
0*
#4790
b10101 4
b110011 :
1)
1*
#4800
0)
0*
#4810
b10110 4
b110100 :
1)
1*
#4820
0)
0*
#4830
b10111 4
b110101 :
1)
1*
#4840
0)
0*
#4850
b11000 4
b110110 :
1)
1*
#4860
0)
0*
#4870
b11001 4
b110111 :
1)
1*
#4880
0)
0*
#4890
b11010 4
b111000 :
1)
1*
#4900
0)
0*
#4910
b11011 4
b111001 :
1)
1*
#4920
0)
0*
#4930
b11100 4
b111010 :
1)
1*
#4940
0)
0*
#4950
b11101 4
b111011 :
1)
1*
#4960
0)
0*
#4970
b11110 4
b111100 :
1)
1*
#4980
0)
0*
#4990
b11111 4
b111101 :
1)
1*
#5000
0)
0*
#5010
b100000 4
b11 9
b0 :
1)
1*
#5020
0)
0*
#5030
b100001 4
b1 :
00
1)
1*
#5040
0)
0*
#5050
b100010 4
b10 :
1)
1*
#5060
0)
0*
